CHANGELOG.md
README.md
make_release/__init__.py
make_release/__main__.py
make_release/merge.py
make_release/prepare.py
make_release/release.py
make_release/resume.py
make_release/tag.py
make_release/util.py
com_wyattbaldwin_make_release-1.0a4.dist-info/WHEEL
com_wyattbaldwin_make_release-1.0a4.dist-info/entry_points.txt
com_wyattbaldwin_make_release-1.0a4.dist-info/METADATA
com_wyattbaldwin_make_release-1.0a4.dist-info/RECORD
