Metadata-Version: 2.1
Name: com-wyattbaldwin-make-release
Version: 1.0a4
Summary: Make a release
Home-page: https://github.com/wylee/com.wyattbaldwin/tree/dev/make-release
Author: Wyatt Baldwin
Author-email: self@wyattbaldwin.com
Requires-Python: >=3.7,<4.0
Classifier: Programming Language :: Python :: 3
Classifier: Programming Language :: Python :: 3.7
Classifier: Programming Language :: Python :: 3.8
Classifier: Programming Language :: Python :: 3.9
Classifier: Programming Language :: Python :: 3.10
Classifier: Programming Language :: Python :: 3.11
Requires-Dist: runcommands (>=1.0a71,<2.0)
Project-URL: Repository, https://github.com/wylee/com.wyattbaldwin/tree/dev/make-release
